README.rst
semverpy.py
setup.cfg
setup.py
SemVerPy.egg-info/PKG-INFO
SemVerPy.egg-info/SOURCES.txt
SemVerPy.egg-info/dependency_links.txt
SemVerPy.egg-info/top_level.txt
test/test_bumping.py
test/test_equality.py
test/test_regex.py
test/test_str.py