Metadata-Version: 1.0
Name: SemVerPy
Version: 0.1.0
Summary: Bump versions. Semantically.
Home-page: https://github.com/Dinoshauer/SemVerPy
Author: Kasper Jacobsen
Author-email: k@mackwerk.dk
License: MIT
Platform: UNKNOWN
